lifeofpy/__init__.py
lifeofpy/lifeofpy.py
lifeofpy-0.0.2.dist-info/LICENSE
lifeofpy-0.0.2.dist-info/METADATA
lifeofpy-0.0.2.dist-info/WHEEL
lifeofpy-0.0.2.dist-info/top_level.txt
lifeofpy-0.0.2.dist-info/RECORD
